static_site/__init__.py
static_site/router.js
static_site/static_site.py
cdk_static_site-0.1.2.dist-info/WHEEL
cdk_static_site-0.1.2.dist-info/METADATA
cdk_static_site-0.1.2.dist-info/RECORD
