Metadata-Version: 2.1
Name: cdk-static-site
Version: 0.1.2
Summary: CDK construct for static websites for CDK v2
Home-page: https://github.com/davidsteiner/cdk-static-site
Author: David Steiner
Author-email: david_j_steiner@yahoo.co.nz
Requires-Python: >=3.9,<4.0
Classifier: Programming Language :: Python :: 3
Classifier: Programming Language :: Python :: 3.10
Classifier: Programming Language :: Python :: 3.9
Requires-Dist: aws-cdk-lib (>=2.28,<3.0)
